cafcore/__init__.py
cafcore/cook_transform.py
cafcore/file_io.py
cafcore/qc.py
cafcore/data/cookeast_georeferencepoint_20190924.geojson
cafcore/data/cookwest_georeferencepoint_20190924.geojson
cafcore-0.1.3.dist-info/METADATA
cafcore-0.1.3.dist-info/WHEEL
cafcore-0.1.3.dist-info/top_level.txt
cafcore-0.1.3.dist-info/RECORD
