Metadata-Version: 2.1
Name: cafcore
Version: 0.1.3
Summary: Core functions used to process data for R.J. Cook Agronomy Farm LTAR
Home-page: https://github.com/cafltar/cafcore
Author: Bryan Carlson
Author-email: bryan.carlson@usda.gov
License: CC0
Classifier: Development Status :: 4 - Beta
Classifier: Intended Audience :: Science/Research
Classifier: Topic :: Scientific/Engineering
Classifier: License :: CC0 1.0 Universal (CC0 1.0) Public Domain Dedication
Classifier: Programming Language :: Python :: 3
Requires-Dist: pathlib
Requires-Dist: pandas
Requires-Dist: numpy
Requires-Dist: geopandas
